{
    "fluentMethods": true,
    "relationships": [],
    "fields": [
        {
            "fieldName": "city",
            "fieldType": "String",
            "fieldValidateRules": [
                "required"
            ]
        },
        {
            "fieldName": "pricePerKilowatt",
            "fieldType": "Double",
            "fieldValidateRules": [
                "min"
            ],
            "fieldValidateRulesMin": 0
        }
    ],
    "changelogDate": "20171117174928",
    "dto": "no",
    "service": "no",
    "entityTableName": "power_cost",
    "jpaMetamodelFiltering": false,
    "pagination": "no"
}
